Metadata-Version: 1.0
Name: hinzkunz
Version: 0.0.1
Summary: Hinz und Kunz
Home-page: https://github.com/alvations/hinz-kunz
Author: UNKNOWN
Author-email: UNKNOWN
License: UNKNOWN
Platform: UNKNOWN
